places_lk/__init__.py
places_lk/core/PLACE_INFO_LIST.py
places_lk/core/PlaceInfo.py
places_lk/core/__init__.py
places_lk/core/search_places.py
utils_future/Alt.py
utils_future/LatLng.py
utils_future/__init__.py
places_lk_nuuuwan-1.0.0.dist-info/LICENSE
places_lk_nuuuwan-1.0.0.dist-info/METADATA
places_lk_nuuuwan-1.0.0.dist-info/WHEEL
places_lk_nuuuwan-1.0.0.dist-info/top_level.txt
places_lk_nuuuwan-1.0.0.dist-info/RECORD
