Metadata-Version: 2.1
Name: places_lk-nuuuwan
Version: 1.0.0
Summary: A utility library for returning the location of places in Sri Lanka.
Home-page: https://github.com/nuuuwan/places_lk
Author: Nuwan I. Senaratna
Author-email: nuuuwan@gmail.com
Project-URL: Bug Tracker, https://github.com/nuuuwan/places_lk/issues
Classifier: Programming Language :: Python :: 3
Classifier: License :: OSI Approved :: MIT License
Classifier: Operating System :: OS Independent
Requires-Python: >=3.10
License-File: LICENSE
Requires-Dist: utils-nuuuwan
